{
  "version": "2.5.3",
  "flags": {},
  "shapes": [
    {
      "label": "blue bin",
      "score": null,
      "points": [
        [
          439.1666666666668,
          254.16666666666669
        ],
        [
          635.8333333333334,
          615.8333333333334
        ],
        [
          765.8333333333334,
          561.6666666666667
        ],
        [
          960.8333333333334,
          440.83333333333337
        ],
        [
          1059.1666666666667,
          381.6666666666667
        ],
        [
          1020.8333333333334,
          357.5
        ],
        [
          956.6666666666666,
          280.0
        ],
        [
          813.3333333333334,
          65.0
        ],
        [
          653.3333333333334,
          148.33333333333334
        ]
      ],
      "group_id": null,
      "description": "",
      "difficult": false,
      "shape_type": "polygon",
      "flags": {},
      "attributes": {},
      "kie_linking": []
    }
  ],
  "imagePath": "color_41.jpg",
  "imageData": null,
  "imageHeight": 720,
  "imageWidth": 1280,
  "description": ""
}